.hgignore
.hgtags
BUGS
CHANGES
COPYING
HACKING
MANIFEST.in
Makefile
README.cvs2hg
README.rst
cvs2hg
cvs2hg-example.options
dist.sh
noxfile.py
run-tests.py
setup.py
.idea/vcs.xml
.idea/runConfigurations/cvs2hg.xml
contrib/__init__.py
contrib/cvs2svn_memlog
contrib/cvsVsvn.pl
contrib/destroy_repository.py
contrib/find_illegal_filenames.py
contrib/profile-repos.py
contrib/rcs_file_filter.py
contrib/renumber_branch.py
contrib/show_db.py
contrib/shrink_test_case.py
contrib/verify-all
contrib/verify-cvs2hg.py
cvs2hg.egg-info/PKG-INFO
cvs2hg.egg-info/SOURCES.txt
cvs2hg.egg-info/dependency_links.txt
cvs2hg.egg-info/top_level.txt
cvs2hg_lib/Makefile
cvs2hg_lib/__init__.py
cvs2hg_lib/apple_single_filter.py
cvs2hg_lib/artifact.py
cvs2hg_lib/artifact_manager.py
cvs2hg_lib/changeset.py
cvs2hg_lib/changeset_database.py
cvs2hg_lib/changeset_graph.py
cvs2hg_lib/changeset_graph_link.py
cvs2hg_lib/changeset_graph_node.py
cvs2hg_lib/check_dependencies_pass.py
cvs2hg_lib/checkout_internal.py
cvs2hg_lib/collect_data.py
cvs2hg_lib/common.py
cvs2hg_lib/compat.py
cvs2hg_lib/config.py
cvs2hg_lib/context.py
cvs2hg_lib/cvs_file_items.py
cvs2hg_lib/cvs_item.py
cvs2hg_lib/cvs_item_database.py
cvs2hg_lib/cvs_path.py
cvs2hg_lib/cvs_path_database.py
cvs2hg_lib/cvs_revision_manager.py
cvs2hg_lib/database.py
cvs2hg_lib/dvcs_common.py
cvs2hg_lib/external_blob_generator.py
cvs2hg_lib/fill_source.py
cvs2hg_lib/generate_blobs.py
cvs2hg_lib/hg_output_option.py
cvs2hg_lib/hg_run_options.py
cvs2hg_lib/key_generator.py
cvs2hg_lib/log.py
cvs2hg_lib/main.py
cvs2hg_lib/man_writer.py
cvs2hg_lib/metadata.py
cvs2hg_lib/metadata_database.py
cvs2hg_lib/openings_closings.py
cvs2hg_lib/output_option.py
cvs2hg_lib/pass_manager.py
cvs2hg_lib/passes.py
cvs2hg_lib/persistence_manager.py
cvs2hg_lib/process.py
cvs2hg_lib/project.py
cvs2hg_lib/property_setters.py
cvs2hg_lib/rcs_revision_manager.py
cvs2hg_lib/rcs_stream.py
cvs2hg_lib/record_table.py
cvs2hg_lib/repository_mirror.py
cvs2hg_lib/repository_walker.py
cvs2hg_lib/revision_manager.py
cvs2hg_lib/run_options.py
cvs2hg_lib/serializer.py
cvs2hg_lib/sort.py
cvs2hg_lib/stats_keeper.py
