Metadata-Version: 2.1
Name: cvs2hg
Version: 3.0.2
Summary: cvs2hg repository converter (based on cvs2svn)
Home-page: https://foss.heptapod.net/mercurial/mercurial-cvs2hg
Author: The cvs2svn team, Greg Ward, Marcin Kasperski
Author-email: Marcin.Kasperski@mekk.waw.pl
License: Apache-style
Classifier: Development Status :: 5 - Production/Stable
Classifier: Environment :: Console
Classifier: Intended Audience :: Developers
Classifier: Intended Audience :: System Administrators
Classifier: License :: OSI Approved
Classifier: Natural Language :: English
Classifier: Operating System :: OS Independent
Classifier: Programming Language :: Python :: 2
Classifier: Topic :: Software Development :: Version Control
Classifier: Topic :: Software Development :: Version Control :: CVS
Classifier: Topic :: Utilities
License-File: COPYING
